mineai/__init__.py
mineai/client.py
mineai/errors.py
mineai/models.py
mineai/resources/chat/completions.py
mineai-1.0.0.dist-info/METADATA
mineai-1.0.0.dist-info/WHEEL
mineai-1.0.0.dist-info/top_level.txt
mineai-1.0.0.dist-info/RECORD
