Metadata-Version: 2.4
Name: mineai
Version: 1.0.0
Summary: The official Python SDK for MineAI
Author-email: MineAI Team <support@getmineai.site>
Project-URL: Homepage, https://studio.getmineai.site
Project-URL: Bug Tracker, https://github.com/OfficalMinecore/mineai-sdk-python/issues
Project-URL: Repository, https://github.com/OfficalMinecore/mineai-sdk-python
Classifier: Programming Language :: Python :: 3
Classifier: License :: OSI Approved :: MIT License
Classifier: Operating System :: OS Independent
Requires-Python: >=3.7
Requires-Dist: httpx>=0.20.0
